Metadata-Version: 2.1
Name: dsnd-distributions-MT
Version: 0.1
Summary: Gaussian and Binomial distributions
Home-page: UNKNOWN
Author: Meng Tan
Author-email: nanco104@gmail.com
License: UNKNOWN
Platform: UNKNOWN
